async_comlink/__init__.py
async_comlink/async_comlink.py
async_comlink/helpers.py
async_comlink/items.py
async_comlink-1.1.0.dist-info/METADATA
async_comlink-1.1.0.dist-info/WHEEL
async_comlink-1.1.0.dist-info/top_level.txt
async_comlink-1.1.0.dist-info/RECORD
