Metadata-Version: 2.1
Name: async-comlink
Version: 1.1.0
Summary: Asynchronous Python wrapper for the swgoh-comlink service
Author: bnziv
License: MIT
Classifier: Programming Language :: Python :: 3
Classifier: License :: OSI Approved :: MIT License
Requires-Dist: aiohttp
